mim/__init__.py
mim/mim.py
mim/util/GithubRepository.py
mim/util/ModrinthRepository.py
mim/util/PaperRepository.py
mim/util/Repository.py
mim/util/SpigetRepository.py
mim/util/__init__.py
minecraft_install_manager-0.0.1.dist-info/licenses/LICENSE
minecraft_install_manager-0.0.1.dist-info/METADATA
minecraft_install_manager-0.0.1.dist-info/WHEEL
minecraft_install_manager-0.0.1.dist-info/entry_points.txt
minecraft_install_manager-0.0.1.dist-info/top_level.txt
minecraft_install_manager-0.0.1.dist-info/RECORD
