Metadata-Version: 2.4
Name: minecraft-install-manager
Version: 0.0.1
Summary: A small CLI to find and download Minecraft server plugins from multiple repositories
Author: thehappykraken
License:                     GNU GENERAL PUBLIC LICENSE
Project-URL: Homepage, https://github.com/thehappykraken/MinecraftPluginManager
Project-URL: Source, https://github.com/thehappykraken/MinecraftPluginManager
Classifier: Programming Language :: Python :: 3
Classifier: Programming Language :: Python :: 3 :: Only
Classifier: License :: OSI Approved :: GNU General Public License v3 (GPLv3)
Classifier: Operating System :: OS Independent
Requires-Python: >=3.11
License-File: LICENSE
Requires-Dist: requests
Dynamic: license-file
